jaxili/__init__.py
jaxili/__version__.py
jaxili/compressor.py
jaxili/loss.py
jaxili/model.py
jaxili/train.py
jaxili/utils.py
jaxili/validation.py
jaxili/inference/__init__.py
jaxili/inference/nle.py
jaxili/inference/npe.py
jaxili/inventory/func_dict.py
jaxili/posterior/__init__.py
jaxili/posterior/base_posterior.py
jaxili/posterior/direct_posterior.py
jaxili/posterior/mcmc_posterior.py
jaxili-0.1.3.dist-info/licenses/LICENSE
jaxili-0.1.3.dist-info/METADATA
jaxili-0.1.3.dist-info/WHEEL
jaxili-0.1.3.dist-info/top_level.txt
jaxili-0.1.3.dist-info/RECORD
