Metadata-Version: 2.4
Name: jaxili
Version: 0.1.3
Summary: This package provides tools to execute and implement Implicit Likelihood Inference tools in JAX.
Author: Sacha Guerrini
Project-URL: Repository, https://github.com/sachaguer/jaxili
Requires-Python: <3.13,>=3.10
License-File: LICENSE
Requires-Dist: numpy
Requires-Dist: jax[cuda12]
Requires-Dist: jax_dataloader
Requires-Dist: jupyter
Requires-Dist: matplotlib
Requires-Dist: cmake
Requires-Dist: tensorflow-cpu
Requires-Dist: tensorflow-probability
Requires-Dist: optax
Requires-Dist: distrax
Requires-Dist: flax
Requires-Dist: optuna
Requires-Dist: numpyro
Requires-Dist: flowMC
Requires-Dist: pytorch-lightning
Requires-Dist: getdist
Provides-Extra: docs
Requires-Dist: myst-parser; extra == "docs"
Requires-Dist: numpydoc; extra == "docs"
Requires-Dist: sphinx; extra == "docs"
Requires-Dist: sphinx-book-theme; extra == "docs"
Requires-Dist: nbsphinx; extra == "docs"
Requires-Dist: tf-keras; extra == "docs"
Provides-Extra: test
Requires-Dist: pytest; extra == "test"
Requires-Dist: pytest-cov; extra == "test"
Requires-Dist: pytest-emoji; extra == "test"
Requires-Dist: pytest-pydocstyle; extra == "test"
Requires-Dist: tf-keras; extra == "test"
Requires-Dist: sbibm; extra == "test"
Requires-Dist: sbi==0.23.3; extra == "test"
Provides-Extra: lint
Requires-Dist: black; extra == "lint"
Requires-Dist: isort; extra == "lint"
Provides-Extra: release
Requires-Dist: build; extra == "release"
Requires-Dist: twine; extra == "release"
Provides-Extra: dev
Requires-Dist: jaxili[docs,lint,release,test]; extra == "dev"
Dynamic: license-file
